{
  "data": {
    "article": {},
    "attachments": {},
    "author_id": "2019293013114253313",
    "conversation_id": "2043901880976454090",
    "created_at": "2026-04-28T15:26:42.000Z",
    "edit_controls": {
      "editable_until": "2026-04-28T16:26:42.000Z",
      "edits_remaining": 5,
      "is_edit_eligible": false
    },
    "edit_history_tweet_ids": [
      "2049148308044865722"
    ],
    "entities": {
      "mentions": [
        {
          "end": 10,
          "id": "2031715041196875776",
          "start": 0,
          "username": "YiJin_0v0"
        },
        {
          "end": 23,
          "id": "2010386046975139841",
          "start": 11,
          "username": "WanXin17900"
        }
      ]
    },
    "geo": {},
    "id": "2049148308044865722",
    "in_reply_to_user_id": "2031715041196875776",
    "lang": "qme",
    "note_tweet": {
      "entities": {}
    },
    "possibly_sensitive": false,
    "public_metrics": {
      "bookmark_count": 0,
      "impression_count": 0,
      "like_count": 0,
      "quote_count": 0,
      "reply_count": 0,
      "retweet_count": 0
    },
    "referenced_tweets": [
      {
        "id": "2049147991102263606",
        "type": "replied_to"
      }
    ],
    "reply_settings": "everyone",
    "text": "@YiJin_0v0 @WanXin17900 🫂"
  },
  "includes": {
    "tweets": [
      {
        "article": {},
        "attachments": {},
        "author_id": "2019293013114253313",
        "conversation_id": "2043901880976454090",
        "created_at": "2026-04-28T15:26:42.000Z",
        "edit_controls": {
          "editable_until": "2026-04-28T16:26:42.000Z",
          "edits_remaining": 5,
          "is_edit_eligible": false
        },
        "edit_history_tweet_ids": [
          "2049148308044865722"
        ],
        "entities": {
          "mentions": [
            {
              "end": 10,
              "id": "2031715041196875776",
              "start": 0,
              "username": "YiJin_0v0"
            },
            {
              "end": 23,
              "id": "2010386046975139841",
              "start": 11,
              "username": "WanXin17900"
            }
          ]
        },
        "geo": {},
        "id": "2049148308044865722",
        "in_reply_to_user_id": "2031715041196875776",
        "lang": "qme",
        "note_tweet": {
          "entities": {}
        },
        "possibly_sensitive": false,
        "public_metrics": {
          "bookmark_count": 0,
          "impression_count": 0,
          "like_count": 0,
          "quote_count": 0,
          "reply_count": 0,
          "retweet_count": 0
        },
        "referenced_tweets": [
          {
            "id": "2049147991102263606",
            "type": "replied_to"
          }
        ],
        "reply_settings": "everyone",
        "text": "@YiJin_0v0 @WanXin17900 🫂"
      },
      {
        "article": {},
        "attachments": {},
        "author_id": "2031715041196875776",
        "conversation_id": "2043901880976454090",
        "created_at": "2026-04-28T15:25:27.000Z",
        "edit_controls": {
          "editable_until": "2026-04-28T16:25:27.000Z",
          "edits_remaining": 5,
          "is_edit_eligible": false
        },
        "edit_history_tweet_ids": [
          "2049147991102263606"
        ],
        "entities": {
          "mentions": [
            {
              "end": 16,
              "id": "2019293013114253313",
              "start": 0,
              "username": "seeyouinthe2999"
            },
            {
              "end": 29,
              "id": "2010386046975139841",
              "start": 17,
              "username": "WanXin17900"
            }
          ]
        },
        "geo": {},
        "id": "2049147991102263606",
        "in_reply_to_user_id": "2019293013114253313",
        "lang": "zh",
        "note_tweet": {
          "entities": {}
        },
        "possibly_sensitive": false,
        "public_metrics": {
          "bookmark_count": 0,
          "impression_count": 3,
          "like_count": 1,
          "quote_count": 0,
          "reply_count": 1,
          "retweet_count": 0
        },
        "referenced_tweets": [
          {
            "id": "2049147787888169432",
            "type": "replied_to"
          }
        ],
        "reply_settings": "everyone",
        "text": "@seeyouinthe2999 @WanXin17900 可以，老公你帮我把账号解开"
      }
    ],
    "users": [
      {
        "created_at": "2026-02-05T06:12:54.000Z",
        "derived": {
          "locations": [
            {
              "country_code": "JP",
              "full_name": "Shibuya-ku, Tōkyō, Japan",
              "geo": {
                "coordinates": [
                  139.69821,
                  35.66404
                ],
                "type": "Point"
              },
              "locality": "Shibuya-ku",
              "region": "Tōkyō",
              "sub_region": "Shibuya-ku"
            }
          ]
        },
        "description": "15岁高中生 oder💊抑郁/焦虑/c-ptsd\n喜欢听摇滚  割🔪  重返未来1999 偶尔发一些意识流诗文\n只要有手机耳机我就在听歌睡觉也在\n被pr80空腹逼疯的胃病患者\n同类来互fo捏\n@seeinMillennium 备用号",
        "entities": {
          "description": {
            "mentions": [
              {
                "end": 112,
                "start": 96,
                "username": "seeinMillennium"
              }
            ]
          },
          "url": {
            "urls": [
              {
                "display_url": "ngl.link/seeyouinthe2999",
                "end": 23,
                "expanded_url": "https://ngl.link/seeyouinthe2999",
                "start": 0,
                "url": "https://t.co/FSmPgqNygM"
              }
            ]
          }
        },
        "id": "2019293013114253313",
        "location": "Shibuya-ku, Tokyo",
        "name": "马库斯爱吃蛋糕💊",
        "pinned_tweet_id": "2045077580290941129",
        "profile_image_url": "https://pbs.twimg.com/profile_images/2022593862368448512/xmnoyp3e_normal.jpg",
        "protected": false,
        "public_metrics": {
          "followers_count": 407,
          "following_count": 452,
          "like_count": 1977,
          "listed_count": 0,
          "media_count": 75,
          "tweet_count": 1021
        },
        "url": "https://t.co/FSmPgqNygM",
        "username": "seeyouinthe2999",
        "verified": false
      },
      {
        "created_at": "2026-03-11T12:53:23.000Z",
        "description": "有事优先联系此账号\n本体 @hg3551019177402 \n老豆 @rinii165892\n无证含糖/家暴党",
        "entities": {
          "description": {
            "mentions": [
              {
                "end": 29,
                "start": 13,
                "username": "hg3551019177402"
              },
              {
                "end": 46,
                "start": 34,
                "username": "rinii165892"
              }
            ]
          }
        },
        "id": "2031715041196875776",
        "location": "出租屋",
        "name": "霖/伊井酱酱酱🍥8964～",
        "pinned_tweet_id": "2047257307072118954",
        "profile_image_url": "https://pbs.twimg.com/profile_images/2047345595497738240/v4nAldhV_normal.jpg",
        "protected": false,
        "public_metrics": {
          "followers_count": 564,
          "following_count": 430,
          "like_count": 2277,
          "listed_count": 1,
          "media_count": 42,
          "tweet_count": 1435
        },
        "username": "YiJin_0v0",
        "verified": false
      },
      {
        "created_at": "2026-01-11T16:20:25.000Z",
        "description": "Kaio \n是挽心呐\n愿意接受新鲜事物 喜欢一切有意思的东西 喜欢听摇滚 08男高中生 LGBT+全友好 不抽烟不喝酒不嗑药的五好青年。\n\nhttps://t.co/Yx4WaRgjjE",
        "entities": {
          "description": {
            "urls": [
              {
                "display_url": "ngl.link/kaio25037",
                "end": 93,
                "expanded_url": "https://ngl.link/kaio25037",
                "start": 70,
                "url": "https://t.co/Yx4WaRgjjE"
              }
            ]
          }
        },
        "id": "2010386046975139841",
        "location": "On your left ",
        "name": "Kaio",
        "pinned_tweet_id": "2043901880976454090",
        "profile_image_url": "https://pbs.twimg.com/profile_images/2041123589752315904/LURxrTEu_normal.jpg",
        "protected": false,
        "public_metrics": {
          "followers_count": 34,
          "following_count": 86,
          "like_count": 526,
          "listed_count": 0,
          "media_count": 31,
          "tweet_count": 342
        },
        "username": "WanXin17900",
        "verified": false
      }
    ]
  }
}